README.md
setup.py
tavalidate/__init__.py
tavalidate/log.py
tavalidate/test_xmls.py
tavalidate/test_xmlv.py
tavalidate/xmls.py
tavalidate/xmlv.py
tavalidate.egg-info/PKG-INFO
tavalidate.egg-info/SOURCES.txt
tavalidate.egg-info/dependency_links.txt
tavalidate.egg-info/requires.txt
tavalidate.egg-info/top_level.txt