Metadata-Version: 2.1
Name: tavalidate
Version: 0.0.6
Summary: Utilities to help you validate and save Tavern response.
Home-page: https://github.com/sohoffice/tavalidate
Author: Douglas Liu
Author-email: douglas@sohoffice.com
License: UNKNOWN
Platform: UNKNOWN
Classifier: Programming Language :: Python :: 3
Classifier: License :: OSI Approved :: MIT License
Classifier: Operating System :: OS Independent
